aa_algorithms_utils/__init__.py
aa_algorithms_utils/athena_data_provider.py
aa_algorithms_utils/logger.py
aa_algorithms_utils/metrics.py
aa_algorithms_utils/s3_client.py
aa_algorithms_utils-0.0.1.dist-info/METADATA
aa_algorithms_utils-0.0.1.dist-info/WHEEL
aa_algorithms_utils-0.0.1.dist-info/licenses/LICENSE
aa_algorithms_utils-0.0.1.dist-info/RECORD
